Workbook
Name \b: #REF!
Name \d: #REF!
Name \f: #REF!
Name \i: #REF!
Name \k: #REF!
Name \l: #REF!
Name \p: #REF!
Name \s: #REF!
Name \w: #REF!
Name _?1: IF(OR(#REF!=0,#REF!=""),"","~")
Name _?2: IF(OR(#REF!="",#REF!=0,#REF!="",#REF!=0),0,IF(#REF!-#REF!=1,0,IF(#REF!=#REF!,0,#REF!-1)))
Name _?3: IF(OR(#REF!="",#REF!=""),IF(#REF!="",0,IF(#REF!=#REF!,0,1)),IF(#REF!=#REF!,IF(#REF!<>#REF!,1,0),IF(#REF!=#REF!,0,IF(OR(#REF!=0,#REF!=""),1,#REF!-#REF!+1))))
Name _?4: IF(#REF!=0,SUM(#REF!),SUM(#REF!)*#REF!)
Name _______________xlfn_IFERROR: #N/A
Name ______________xlfn_IFERROR: "#N/A"
Name _____________xlfn_IFERROR: "#N/A"
Name ____________xlfn_IFERROR: "#N/A"
Name ___________xlfn_IFERROR: "#N/A"
Name __________xlfn_IFERROR: "#N/A"
Name __________z: NA()
Name _________xlfn_IFERROR: "#N/A"
Name _________z: NA()
Name ________0_1: "#REF!"
Name ________Reg10: [1]Sheet3!$H$34:$H$38
Name ________Reg2: [1]Sheet3!$H$5:$H$12
Name ________Reg3: [1]Sheet3!$H$13
Name ________Reg4: [1]Sheet3!$H$14:$H$18
Name ________Reg5: [1]Sheet3!$H$19:$H$20
Name ________Reg6: [1]Sheet3!$H$21:$H$26
Name ________Reg7: [1]Sheet3!$H$27
Name ________Reg8: [1]Sheet3!$H$28:$H$32
Name ________Reg9: [1]Sheet3!$H$33
Name ________xlfn_IFERROR: "#N/A"
Name ________z: NA()
Name _______0_1: "#REF!"
Name _______0_2: "#REF!"
Name _______b: "#REF!"
Name _______d: "#REF!"
Name _______f: "#REF!"
Name _______i: "#REF!"
Name _______k: "#REF!"
Name _______l: "#REF!"
Name _______p: "#REF!"
Name _______Reg1: #REF!
Name _______Reg10: #REF!
Name _______Reg2: #REF!
Name _______Reg3: [1]Sheet3!$H$13
Name _______Reg4: #REF!
Name _______Reg5: #REF!
Name _______Reg6: #REF!
Name _______Reg7: [1]Sheet3!$H$27
Name _______Reg8: #REF!
Name _______Reg9: [1]Sheet3!$H$33
Name _______s: "#REF!"
Name _______w: "#REF!"
Name _______xlfn_IFERROR: "#N/A"
Name _______z: NA()
Name ______0_1: "#REF!"
Name ______0_2: "#REF!"
Name ______b: "#REF!"

Sheet INV-PO04774
A2: CONTINENT 8 PTE LTD | H2: PO # | I2: PO04774
A3: 300 TAMPINES AVENUE 5, #. 09-02, | H3: Invoice # | I3: 022C8P2605AW26
A4: INCOME AT TAMPINES JUNCTION SINGAPORE 529653 | H4: Date | I4: 46149
A5: AT TAMPINES JUNCTION SINGAPORE 529653 | H5: Shipping Mode | I5: SEA (INCRES 072N)
H6: Shipment # | I6: LGINBSHIP000798
A7: Manufacturer : | H7: ETD Date | I7: 46153
A8: PT. MASTERINDO JAYA ABADI | H8: ETA Date | I8: 46203
A9: JL. SOEKARNO HATTA NO. 24 | H9: Port of Loading | I9: JAKARTA, INDONESIA
A10: BANDUNG 40212, INDONESIA 50512 | H10: Port of Discharge | I10: LOS ANGLES, USA
A11: TAX ID#. 001.280.264.1-441.000 | H11: Remarks
A12: Commercial invoice | H12: Country of Origin | I12: INDONESIA
A14: Consignee | D14: Notify Party
A15: Tentree c/o NRI Distribution Inc. | D15: Tentree International Canada
A16: 9988 Redwood Avenue | D16: 230-1275 Venables St.
A17: LH Building | D17: Vancouver, BC V6A 2E4
A18: Fontana, California | D18: Canada
A19: 1.323.345.6456 | D19: +7789897887
A20: 92335, United States | D20: logstics@tentree.com
A21: Contact: Yarumi Padilla
A22: 1.323.345.6456
A23: yarumi.padilla@nri-distribution.com
A24: Carrier Appointment Email
A25: appt-LH@nri distribution.com
A27: PO# | B27: STYLE-COLOR | C27: Knit/Woven | D27: Style Description | E27: Color Description | F27: Category | G27: Gender | H27: Composition | I27: HTS Code | J27: Quantity | K27: Unit Price USD | L27: Total USD
A28: =I2 -> PO04774 | B28: TCW6649-6303 | C28: Knit | D28: W Flint Pant | E28: Ashwood | F28: Pants | G28: Womens | H28: 53% Organic Cotton, 45% Recycled Polyester, 2% Spandex | I28: 6104.62.62.20 | J28: 40 | K28: 23.35 | L28: =J28*K28 -> 934 | M28: 39.69 | N28: 52.92
A29: =A28 -> PO04774 | B29: TCW6649-0164 | C29: Knit | D29: =D28 -> W Flint Pant | E29: Meteorite Black | F29: Pants | G29: Womens | H29: 53% Organic Cotton, 45% Recycled Polyester, 2% Spandex | I29: 6104.62.62.20 | J29: 49 | K29: 23.35 | L29: =J29*K29 -> 1144.15
A30: =A28 -> PO04774 | B30: TCM6684-6303 | C30: Knit | D30: M Clark Pant | E30: Ashwood | F30: Pants | G30: Mens | H30: 53% Organic Cotton, 45% Recycled Polyester, 2% Spandex | I30: 6103.42.62.20 | J30: 50 | K30: 25.4 | L30: =J30*K30 -> 1270 | M30: 45 | N30: 60
A31: =A28 -> PO04774 | B31: TCM6684-0164 | C31: Knit | D31: =D30 -> M Clark Pant | E31: Meteorite Black | F31: Pants | G31: Mens | H31: =H30 -> 53% Organic Cotton, 45% Recycled Polyester, 2% Spandex | I31: 6103.42.62.20 | J31: 42 | K31: 25.4 | L31: =J31*K31 -> 1066.8
A32: =A30 -> PO04774 | B32: TCW6648-6303 | C32: Woven | D32: W Breton Pant | E32: Ashwood | F32: Pants | G32: Womens | H32: 90% Recycled Polyester, 10% Spandex | I32: 6204.63.62.10 | J32: 79 | K32: 21.85 | L32: =J32*K32 -> 1726.15 | M32: 48.12 | N32: 64.16
A33: =A28 -> PO04774 | B33: TCW6648-0164 | C33: Woven | D33: W Breton Pant | E33: Meteorite Black | F33: Pants | G33: Womens | H33: 90% Recycled Polyester, 10% Spandex | I33: 6204.63.62.10 | J33: 75 | K33: 21.85 | L33: =J33*K33 -> 1638.75
A34: =A28 -> PO04774 | B34: TCM6685-0164 | C34: Woven | D34: M Cameron Pant | E34: Meteorite Black | F34: Pants | G34: Mens | H34: 90% Recycled Polyester, 10% Spandex | I34: 6203.43.62.10 | J34: =+'PL-PO04774'!N118 -> 47 | K34: 27.48 | L34: =J34*K34 -> 1291.56 | M34: 73.86
A35: =A32 -> PO04774 | B35: TCM6685-6289 | C35: Woven | D35: M Cameron Pant | E35: Cedar Bark | F35: Pants | G35: Mens | H35: 90% Recycled Polyester, 10% Spandex | I35: 6203.43.62.10 | J35: =+'PL-PO04774'!N119 -> 35 | K35: 27.48 | L35: =J35*K35 -> 961.8 | M35: 73.86 | N35: 98.48
A36: =A35 -> PO04774 | B36: TCW7113-6303 | C36: Woven | D36: W Cowen Pant | E36: Ashwood | F36: Pants | G36: Womens | H36: 90% Recycled Polyester, 10% Spandex | I36: 6204.63.62.10 | J36: 41 | K36: 22.5 | L36: =J36*K36 -> 922.5 | M36: 50.01 | N36: 66.68
A37: =A28 -> PO04774 | B37: TCW7113-0164 | C37: Woven | D37: W Cowen Pant | E37: Meteorite Black | F37: Pants | G37: Womens | H37: 90% Recycled Polyester, 10% Spandex | I37: 6204.63.62.10 | J37: 27 | K37: 22.5 | L37: =J37*K37 -> 607.5
A38: =A36 -> PO04774 | B38: TCM6797-0164 | C38: Woven | D38: M Simcoe Pant | E38: Meteorite Black | F38: Pants | G38: Mens | H38: 90% Recycled Polyester, 10% Spandex | I38: 6203.43.62.10 | J38: 46 | K38: 22.11 | L38: =J38*K38 -> 1017.06 | M38: 38.14 | N38: 57.21
A39: =A30 -> PO04774 | B39: TCW5674-6391 | C39: Woven | D39: W Yaletown Skirt | E39: Meteorite Black/Meadowland Ditsy | F39: Pants | G39: Womens | H39: 100% ECOVERO -Sustainable Viscose by Lenzing | I39: 6204.63.62.10 | J39: 149 | K39: 14.73 | L39: =J39*K39 -> 2194.77 | M39: 23.1 | N39: 34.65
J41: =SUM(J28:J40) -> 680 | L41: =SUM(L28:L40) -> 14775.04
A42: Say Tn Words Total US Dollars: | C42: Fourteen thousand seven hundred seventy five ad cents four only | M42: =J41+'INV-PO04786'!J35 -> 819 | P42: =52.92*6 -> 317.52
P43: 160
A44: Additional Remarks
A46: UNITED OVERSEAS BANK | G46: CONTINENT 8 PTE LTD | N46: =5865.64-N42-N43 -> 5865.64
A47: 80 RAFFLES PLACE, UOB PLAZA, SINGAPORE | N47: =N46+P42+P43 -> 6343.16
A48: 48624
A49: Swift: UOVBSGSGXXX | N49: =N47-L41 -> -8431.88
A50: Acccount#: 4509022652 (USD)
D55: =L41+'INV-PO04786'!L35 -> 18078.36

Sheet PL-PO04774
A1: =+'INV-PO04774'!A2 -> CONTINENT 8 PTE LTD
A2: =+'INV-PO04774'!A3 -> 300 TAMPINES AVENUE 5, #. 09-02,
A3: =+'INV-PO04774'!A4 -> INCOME AT TAMPINES JUNCTION SINGAPORE 529653
A4: =+'INV-PO04774'!A5 -> AT TAMPINES JUNCTION SINGAPORE 529653
A5: PACKING LIST
J6: PO # | K6: =+'INV-PO04774'!I2 -> PO04774
A7: Consignee | F7: Notify Party | J7: Invoice NO. | K7: =+'INV-PO04774'!I3 -> 022C8P2605AW26
A8: =+'INV-PO04774'!A15 -> Tentree c/o NRI Distribution Inc. | F8: =+'INV-PO04774'!D15 -> Tentree International Canada | J8: S/C NO. | K8: -
A9: =+'INV-PO04774'!A16 -> 9988 Redwood Avenue | F9: =+'INV-PO04774'!D16 -> 230-1275 Venables St. | J9: Packinglist No. | K9: =K7 -> 022C8P2605AW26
A10: =+'INV-PO04774'!A17 -> LH Building | F10: =+'INV-PO04774'!D17 -> Vancouver, BC V6A 2E4 | J10: DATE: | K10: =+'INV-PO04774'!I4 -> 46149
A11: =+'INV-PO04774'!A18 -> Fontana, California | F11: =+'INV-PO04774'!D18 -> Canada | J11: PAGE: | K11: 1-2, 2-2,3-3
A12: =+'INV-PO04774'!A19 -> 1.323.345.6456 | F12: =+'INV-PO04774'!D19 -> +7789897887
A13: =+'INV-PO04774'!A20 -> 92335, United States | F13: =+'INV-PO04774'!D20 -> logstics@tentree.com
A14: =+'INV-PO04774'!A21 -> Contact: Yarumi Padilla
A15: =+'INV-PO04774'!A22 -> 1.323.345.6456
A16: =+'INV-PO04774'!A23 -> yarumi.padilla@nri-distribution.com
A17: =+'INV-PO04774'!A24 -> Carrier Appointment Email
A19: CTN # | D19: PO # | E19: SKU | F19: UPC | G19: Style Description | H19: Color Description | I19: TOTAL CTN | J19: TOTAL PCS/CTN | K19: TOTAL PCS | L19: N/W (Kgs) | M19: G/W (Kgs) | N19: MEASURE (M3) | O19: MEASURE (CM)
A21: 1 | B21: - | C21: =+A21+I21-1 -> 1 | D21: =K6 -> PO04774 | E21: TCW6649-6303-2 | F21: 661814875897 | G21: =+'INV-PO04774'!D28 -> W Flint Pant | H21: =+'INV-PO04774'!E28 -> Ashwood | I21: 1 | J21: 1 | K21: =J21+J22+J23+J24 -> 24 | L21: =540*J21/1000+560*J22/1000+580*J23/1000+600*J24/1000 -> 14 | M21: =1.65+L21 -> 15.65 | N21: 80 X 44 X 25 | O21: 2 | P21: 285 | Q21: 661814875897 | R21: 2
E22: TCW6649-6303-4 | F22: 661814875873 | J22: 6 | Q22: 661814875873 | R22: 4
E23: TCW6649-6303-6 | F23: 661814875859 | J23: 5 | Q23: 661814875859 | R23: 6
E24: TCW6649-6303-8 | F24: 661814875835 | J24: 12 | Q24: 661814875835 | R24: 8
A25: =A21+I21 -> 2 | B25: - | C25: =+A25+I25-1 -> 2 | E25: TCW6649-6303-10 | F25: 661814875972 | I25: 1 | J25: 9 | K25: =J25+J26+J27+J28 -> 16 | L25: =620*J25/1000+640*J26/1000+660*J27/1000+680*J28/1000 -> 10.14 | M25: =1.65+L25 -> 11.79 | N25: 80 X 44 X 15 | Q25: 661814875972 | R25: 10
E26: TCW6649-6303-12 | F26: 661814875958 | J26: 4 | Q26: 661814875958 | R26: 12
E27: TCW6649-6303-14 | F27: 661814875934 | J27: 2 | Q27: 661814875934 | R27: 14
E28: TCW6649-6303-16 | F28: 661814875910 | J28: 1 | Q28: 661814875910 | R28: 16
A29: =A25+I25 -> 3 | B29: - | C29: =+A29+I29-1 -> 3 | E29: TCW6649-0164-2 | F29: 661814876030 | H29: =+'INV-PO04774'!E29 -> Meteorite Black | I29: 1 | J29: 2 | K29: =J29+J30+J31+J32 -> 30 | L29: =540*J29/1000+560*J30/1000+580*J31/1000+600*J32/1000 -> 17.46 | M29: =1.65+L29 -> 19.11 | N29: 80 X 44 X 25 | Q29: 661814876030 | R29: 2
E30: TCW6649-0164-4 | F30: 661814876016 | J30: 8 | Q30: 661814876016 | R30: 4
E31: TCW6649-0164-6 | F31: 661814875996 | J31: 5 | Q31: 661814875996 | R31: 6
E32: TCW6649-0164-8 | F32: 661814876054 | J32: 15 | Q32: 661814876054 | R32: 8
A33: =A29+I29 -> 4 | B33: - | C33: =+A33+I33-1 -> 4 | E33: TCW6649-0164-10 | F33: 661814876139 | I33: 1 | J33: 10 | K33: =J33+J34+J35+J36 -> 19 | L33: =620*J33/1000+640*J34/1000+660*J35/1000+680*J36/1000 -> 12.1 | M33: =1.65+L33 -> 13.75 | N33: 80 X 44 X 15 | Q33: 661814876139 | R33: 10
E34: TCW6649-0164-12 | F34: 661814876115 | J34: 4 | Q34: 661814876115 | R34: 12
E35: TCW6649-0164-14 | F35: 661814876092 | J35: 3 | Q35: 661814876092 | R35: 14
E36: TCW6649-0164-16 | F36: =Q36 -> 661814876078 | J36: 2 | O36: 4 | P36: 288 | Q36: 661814876078 | R36: 16
A37: 1 | B37: - | C37: =+A37+I37-1 -> 1 | D37: =K6 -> PO04774 | E37: TCM6684-6303-30 | F37: 661814885612 | G37: =+'INV-PO04774'!D30 -> M Clark Pant | H37: =+'INV-PO04774'!E30 -> Ashwood | I37: 1 | J37: 4 | K37: =J37+J38+J39+J40 -> 29 | L37: =540*J37/1000+560*J38/1000+580*J39/1000+600*J40/1000 -> 16.74 | M37: =1.65+L37 -> 18.39 | N37: 80 X 44 X 25 | O37: 2 | P37: 285 | Q37: 661814885612 | R37: 30
E38: TCM6684-6303-31 | F38: 661814885599 | J38: 8 | Q38: 661814885599 | R38: 31
E39: TCM6684-6303-32 | F39: 661814885575 | J39: 5 | Q39: 661814885575 | R39: 32
E40: TCM6684-6303-33 | F40: 661814885551 | J40: 12 | Q40: 661814885551 | R40: 33
A41: =A37+I37 -> 2 | B41: - | C41: =+A41+I41-1 -> 2 | E41: TCM6684-6303-34 | F41: 661814885537 | I41: 1 | J41: 10 | K41: =J41+J42+J43+J44 -> 21 | L41: =620*J41/1000+640*J42/1000+660*J43/1000+680*J44/1000 -> 13.54 | M41: =1.65+L41 -> 15.19 | N41: 80 X 44 X 25 | Q41: 661814885537 | R41: 34
E42: TCM6684-6303-36 | F42: 661814885513 | J42: 2 | Q42: 661814885513 | R42: 36
E43: TCM6684-6303-38 | F43: 661814885490 | J43: 3 | Q43: 661814885490 | R43: 38
E44: TCM6684-6303-40 | F44: =Q44 -> 661814885476 | J44: 6 | Q44: 661814885476 | R44: 40
A45: =A41+I41 -> 3 | B45: - | C45: =+A45+I45-1 -> 3 | E45: TCM6684-0164-30 | F45: 661814885773 | H45: =+'INV-PO04774'!E31 -> Meteorite Black | I45: 1 | J45: 3 | K45: =J45+J46+J47+J48 -> 26 | L45: =540*J45/1000+560*J46/1000+580*J47/1000+600*J48/1000 -> 15.04 | M45: =1.65+L45 -> 16.69 | N45: 80 X 44 X 25 | Q45: 661814885773 | R45: 30
E46: TCM6684-0164-31 | F46: 661814885759 | J46: 8 | Q46: 661814885759 | R46: 31
E47: TCM6684-0164-32 | F47: 661814885735 | J47: 3 | Q47: 661814885735 | R47: 32
E48: TCM6684-0164-33 | F48: 661814885711 | J48: 12 | Q48: 661814885711 | R48: 33
A49: =A45+I45 -> 4 | B49: - | C49: =+A49+I49-1 -> 4 | E49: TCM6684-0164-34 | F49: 661814885698 | I49: 1 | J49: 8 | K49: =J49+J50+J51+J52 -> 16 | L49: =620*J49/1000+640*J50/1000+660*J51/1000+680*J52/1000 -> 10.22 | M49: =1.65+L49 -> 11.87 | N49: 80 X 44 X 15 | Q49: 661814885698 | R49: 34
E50: TCM6684-0164-36 | F50: 661814885674 | J50: 3 | Q50: 661814885674 | R50: 36
E51: TCM6684-0164-38 | F51: 661814885650 | J51: 3 | Q51: 661814885650 | R51: 38
E52: TCM6684-0164-40 | F52: 661814885636 | J52: 2 | O52: 4 | P52: 288 | Q52: 661814885636 | R52: 40
A53: 1 | B53: - | C53: =+A53+I53-1 -> 1 | D53: =K6 -> PO04774 | E53: TCW6648-6303-2 | F53: 661814877211 | G53: =+'INV-PO04774'!D32 -> W Breton Pant | H53: =+'INV-PO04774'!E32 -> Ashwood | I53: 1 | J53: 3 | K53: =J53+J54+J55+J56 -> 46 | L53: =340*J53/1000+350*J54/1000+360*J55/1000+370*J56/1000 -> 16.61 | M53: =1.65+L53 -> 18.26 | N53: 80 X 44 X 25 | O53: 2 | P53: 285 | Q53: 661814877211 | R53: 2
E54: TCW6648-6303-4 | F54: 661814877198 | J54: 11 | Q54: 661814877198 | R54: 4
E55: TCW6648-6303-6 | F55: 661814876177 | J55: 10 | Q55: 661814876177 | R55: 6
E56: TCW6648-6303-8 | F56: 661814876153 | J56: 22 | Q56: 661814876153 | R56: 8
A57: =A53+I53 -> 2 | B57: - | C57: =A57+I53-1 -> 2 | E57: TCW6648-6303-10 | F57: 661814877297 | I57: 1 | J57: 17 | K57: =J57+J58+J59+J60 -> 33 | L57: =380*J57/1000+390*J58/1000+400*J59/1000+410*J60/1000 -> 12.81 | M57: =1.65+L57 -> 14.46 | N57: 80 X 44 X 25 | Q57: 661814877297 | R57: 10
E58: TCW6648-6303-12 | F58: 661814877273 | J58: 8 | Q58: 661814877273 | R58: 12
E59: TCW6648-6303-14 | F59: 661814877259 | J59: 5 | Q59: 661814877259 | R59: 14
E60: TCW6648-6303-16 | F60: 661814877235 | J60: 3 | Q60: 661814877235 | R60: 16
A61: =A57+I57 -> 3 | B61: - | C61: =+A61+I61-1 -> 3 | E61: TCW6648-0164-2 | F61: 661814877372 | G61: =G53 -> W Breton Pant | H61: =+'INV-PO04774'!E33 -> Meteorite Black | I61: 1 | J61: 3 | K61: =J61+J62+J63+J64 -> 44 | L61: =340*J61/1000+350*J62/1000+360*J63/1000+370*J64/1000 -> 15.89 | M61: =1.65+L61 -> 17.54 | N61: 80 X 44 X 25 | Q61: 661814877372 | R61: 2
E62: TCW6648-0164-4 | F62: 661814877358 | J62: 10 | Q62: 661814877358 | R62: 4
E63: TCW6648-0164-6 | F63: 661814877334 | J63: 10 | Q63: 661814877334 | R63: 6
E64: TCW6648-0164-8 | F64: 661814877310 | J64: 21 | Q64: 661814877310 | R64: 8
A65: =A61+I61 -> 4 | B65: - | C65: =A65+I61-1 -> 4 | E65: TCW6648-0164-10 | F65: 661814877457 | I65: 1 | J65: 16 | K65: =J65+J66+J67+J68 -> 31 | L65: =380*J65/1000+390*J66/1000+400*J67/1000+410*J68/1000 -> 12.04 | M65: =1.65+L65 -> 13.69 | N65: 80 X 44 X 25 | Q65: 661814877457 | R65: 10
E66: TCW6648-0164-12 | F66: 661814877433 | J66: 7 | Q66: 661814877433 | R66: 12
E67: TCW6648-0164-14 | F67: 661814877419 | J67: 5 | Q67: 661814877419 | R67: 14
E68: TCW6648-0164-16 | F68: 661814877396 | J68: 3 | Q68: 661814877396 | R68: 16
A69: 1 | B69: - | C69: =+A69+I69-1 -> 1 | D69: =K6 -> PO04774 | E69: TCM6685-0164-30 | F69: 6618104885452 | G69: =+'INV-PO04774'!D35 -> M Cameron Pant | H69: =+'INV-PO04774'!E34 -> Meteorite Black | I69: 1 | J69: 4 | K69: =J69+J70+J71+J72+J73+J74+J75+J76 -> 47 | L69: =234*K69/1000 -> 10.998 | M69: =1.65+L69 -> 12.648 | N69: 80 X 44 X 25 | O69: XS | P69: 209 | Q69: 661814885452 | R69: 30
E70: TCM6685-0164-31 | F70: 6618104885438 | J70: 4 | O70: S | P70: 219 | Q70: 661814885438 | R70: 31
E71: TCM6685-0164-32 | F71: 6618104885414 | J71: 8 | O71: M | P71: 234 | Q71: 661814885414 | R71: 32
E72: TCM6685-0164-33 | F72: 6618104885391 | J72: 7 | O72: L | P72: 249 | Q72: 661814885391 | R72: 33
E73: TCM6685-0164-34 | F73: 6618104885377 | J73: 9 | O73: XK | P73: 253 | Q73: 661814885377 | R73: 34
E74: TCM6685-0164-36 | F74: 6618104885339 | J74: 10 | Q74: 661814885339 | R74: 36
E75: TCM6685-0164-38 | F75: 6618104885315 | J75: 3 | Q75: 661814885315 | R75: 38
E76: TCM6685-0164-40 | F76: 6618104885292 | J76: 2 | Q76: 661814885292 | R76: 40
A77: =A69+I69 -> 2 | B77: - | C77: =+A77+I77-1 -> 2 | E77: TCM6685-6289-30 | F77: 6618104893112 | H77: =+'INV-PO04774'!E35 -> Cedar Bark | I77: 1 | J77: 3 | K77: =J77+J78+J79+J80+J81+J82+J83+J84 -> 35 | L77: =234*K77/1000 -> 8.19 | M77: =1.65+L77 -> 9.84 | N77: 80 X 44 X 25 | Q77: 661814893112 | R77: 30
E78: TCM6685-6289-31 | F78: 6618104893099 | J78: 3 | Q78: 661814893099 | R78: 31
E79: TCM6685-6289-32 | F79: 6618104893075 | J79: 6 | Q79: 661814893075 | R79: 32
E80: TCM6685-6289-33 | F80: 6618104893051 | J80: 5 | Q80: 661814893051 | R80: 33
E81: TCM6685-6289-34 | F81: 6618104893037 | J81: 7 | Q81: 661814893037 | R81: 34
E82: TCM6685-6289-36 | F82: 6618104893013 | J82: 8 | Q82: 661814893013 | R82: 36
E83: TCM6685-6289-38 | F83: 6618104892993 | J83: 2 | Q83: 661814892993 | R83: 38
E84: TCM6685-6289-40 | F84: 6618104892979 | J84: 1 | Q84: 661814892979 | R84: 40
A85: 1 | B85: - | C85: 1 | D85: =K6 -> PO04774 | E85: TCM7113-6303 -XS | F85: 661814939698 | G85: =+'INV-PO04774'!D36 -> W Cowen Pant | H85: =+'INV-PO04774'!E36 -> Ashwood | I85: 1 | J85: 2 | K85: 41 | L85: 15.78 | M85: 16.5 | N85: 80 X 44 X 25 | Q85: 661814939698 | R85: XS
E86: TCM7113-6303 -S | F86: 661814939711 | J86: 8 | Q86: 661814939711 | R86: S
E87: TCM7113-6303-M | F87: 661814939728 | J87: 15 | Q87: 661814939728 | R87: M
E88: TCM7113-6303 -L | F88: 661814939435 | J88: 10 | Q88: 661814939735 | R88: L
E89: TCM7113-6303 -XL | F89: 661814939704 | J89: 6 | Q89: 661814939704 | R89: XL
A90: 2 | B90: - | C90: 2 | E90: TCM7113-0164-XS | F90: =Q90 -> 661814939742 | H90: =+'INV-PO04774'!E37 -> Meteorite Black | I90: 1 | J90: 1 | K90: 27 | L90: 10.42 | M90: 11.14 | N90: 80 X 44 X 25 | O90: 2 | P90: 285 | Q90: 661814939742 | R90: XS
E91: TCM7113-0164 -S | F91: =Q91 -> 661814939766 | J91: 5 | O91: 4 | P91: 288 | Q91: 661814939766 | R91: S
E92: TCM7113-0164 -M | F92: =Q92 -> 661814939773 | J92: 10 | O92: 6 | P92: 292 | Q92: 661814939773 | R92: M
E93: TCM7113-0164 -L | F93: =Q93 -> 661814939780 | J93: 7 | O93: 8 | P93: 296 | Q93: 661814939780 | R93: L
E94: TCM7113-0164 -XL | F94: =Q94 -> 661814939759 | J94: 4 | O94: 10 | P94: 307 | Q94: 661814939759 | R94: XL
A95: 1 | B95: - | C95: =+A95+I95-1 -> 1 | D95: =K6 -> PO04774 | E95: TCM6797-0164 -L | F95: 661814824833 | G95: =+'INV-PO04774'!D32 -> W Breton Pant | H95: =+'INV-PO04774'!E38 -> Meteorite Black | I95: 1 | J95: 15 | K95: 46 | L95: 19.1 | M95: 19.82 | N95: 80 X 44 X 25 | O95: 2 | P95: 285 | Q95: 661814824833 | R95: L
E96: TCM6797-0164 -M | F96: 661814824819 | J96: 15 | O96: 4 | P96: 288 | Q96: 661814824819 | R96: M
E97: TCM6797-0164 -S | F97: 661814824796 | J97: 5 | O97: 6 | P97: 292 | Q97: 661814824796 | R97: S
E98: TCM6797-0164 -XL | F98: 661814824772 | J98: 8 | O98: 8 | P98: 296 | Q98: 661814824772 | R98: XL
E99: TCM6797-0164 -XXL | F99: 661814824758 | J99: 3 | O99: 10 | P99: 307 | Q99: 661814824758 | R99: XXL
A100: 1 | B100: - | C100: =+A100+I100-1 -> 1 | D100: =D21 -> PO04774 | E100: TCW5674-6391-XS | F100: 661814888989 | G100: =+'INV-PO04774'!D39 -> W Yaletown Skirt | H100: =+'INV-PO04774'!E39 -> Meteorite Black/Meadowland Ditsy | I100: 1 | J100: 8 | K100: =J100+J101+J102 -> 80 | L100: =150*J100/1000+170*J101/1000+190*J102/1000 -> 14.18 | M100: =1.65+L100 -> 15.83 | N100: 80 X 44 X 25 | O100: 2 | P100: 285 | Q100: 661814888989 | R100: XS
E101: TCW5674-6391-S | F101: 661814889023 | J101: 35 | O101: 4 | P101: 288 | Q101: 661814889023 | R101: S
E102: TCW5674-6391-M | F102: 661814889047 | J102: 37 | O102: 6 | P102: 292 | Q102: 661814889047 | R102: M
...

Sheet INV-PO04786
A2: CONTINENT 8 PTE LTD | H2: PO # | I2: PO04786
A3: 300 TAMPINES AVENUE 5, #. 09-02, | H3: Invoice # | I3: 022C8P2605AW26.A
A4: INCOME AT TAMPINES JUNCTION SINGAPORE 529653 | H4: Date | I4: 46149
A5: AT TAMPINES JUNCTION SINGAPORE 529653 | H5: Shipping Mode | I5: SEA (INCRES 072N)
H6: Shipment # | I6: LGINBSHIP000798
A7: Manufacturer : | H7: ETD Date | I7: 46153
A8: PT. MASTERINDO JAYA ABADI | H8: ETA Date | I8: 46203
A9: JL. SOEKARNO HATTA NO. 24 | H9: Port of Loading | I9: JAKARTA, INDONESIA
A10: BANDUNG 40212, INDONESIA 50512 | H10: Port of Discharge | I10: LOS ANGLES, USA
A11: TAX ID#. 001.280.264.1-441.000 | H11: Remarks
A12: Commercial invoice | H12: Country of Origin | I12: INDONESIA
A14: Consignee | D14: Notify Party
A15: Tentree c/o NRI Distribution Inc. - RECEIVING | D15: Tentree International Canada
A16: 9988 Redwood Avenue | D16: 230-1275 Venables St.
A17: LH Building | D17: Vancouver, BC V6A 2E4
A18: Fontana, California | D18: Canada
A19: 1.323.345.6456 | D19: +7789897887
A20: 92335, United States | D20: logstics@tentree.com
A21: Contact: Yarumi Padilla
A22: 1.323.345.6456
A23: yarumi.padilla@nri-distribution.com
A24: Carrier Appointment Email
A25: appt-LH@nri distribution.com
A27: PO# | B27: STYLE-COLOR | C27: Knit/Woven | D27: Style Description | E27: Color Description | F27: Category | G27: Gender | H27: Composition | I27: HTS Code | J27: Quantity | K27: Unit Price USD | L27: Total USD
A28: =I2 -> PO04786 | B28: TCW6649-6303 | C28: Knit | D28: W Flint Pant | E28: Ashwood | F28: Pants | G28: Womens | H28: 53% Organic Cotton, 45% Recycled Polyester, 2% Spandex | I28: 6104.62.62.20 | J28: 27 | K28: 23.35 | L28: =J28*K28 -> 630.45 | M28: 39.69 | N28: 52.92
A29: =A28 -> PO04786 | B29: TCW6649-0164 | C29: Knit | D29: =D28 -> W Flint Pant | E29: Meteorite Black | F29: Pants | G29: Womens | H29: 53% Organic Cotton, 45% Recycled Polyester, 2% Spandex | I29: 6104.62.62.20 | J29: 29 | K29: 23.35 | L29: =J29*K29 -> 677.15
A30: =A28 -> PO04786 | B30: TCM6684-6303 | C30: Knit | D30: M Clark Pant | E30: Ashwood | F30: Pants | G30: Mens | H30: 53% Organic Cotton, 45% Recycled Polyester, 2% Spandex | I30: 6103.42.62.20 | J30: 18 | K30: 25.4 | L30: =J30*K30 -> 457.2 | M30: 45 | N30: 60
A31: =A30 -> PO04786 | B31: TCM6684-0164 | C31: Knit | D31: =D30 -> M Clark Pant | E31: Meteorite Black | F31: Pants | G31: Mens | H31: =H30 -> 53% Organic Cotton, 45% Recycled Polyester, 2% Spandex | I31: 6103.42.62.20 | J31: 51 | K31: 25.4 | L31: =J31*K31 -> 1295.4
A32: =A28 -> PO04786 | B32: TCM6797-0164 | C32: Woven | D32: M Simcoe Pant | E32: Cedar Bark | F32: Pants | G32: Mens | H32: 90% Recycled Polyester, 10% Spandex | I32: 6203.43.62.10 | J32: 5 | K32: 22.11 | L32: =J32*K32 -> 110.55 | M32: 38.14 | N32: 57.21
A33: =A30 -> PO04786 | B33: TCW5674-6391 | C33: Woven | D33: W Yaletown Skirt | E33: Meteorite Black/Meadowland Ditsy | F33: Pants | G33: Womens | H33: 100% ECOVERO -Sustainable Viscose by Lenzing | I33: 6204.63.62.10 | J33: 9 | K33: 14.73 | L33: =J33*K33 -> 132.57 | M33: 23.1 | N33: 34.65
J35: =SUM(J28:J34) -> 139 | L35: =SUM(L28:L34) -> 3303.32
A36: Say Tn Words Total US Dollars: | C36: Three thousand three hundred three and cents thirty two only | N36: =52.94*6 -> 317.64 | P36: =52.92*6 -> 317.52
N37: 161.6 | P37: 160
A38: Additional Remarks
A40: UNITED OVERSEAS BANK | G40: CONTINENT 8 PTE LTD | N40: =5865.64-N36-N37 -> 5386.4
A41: 80 RAFFLES PLACE, UOB PLAZA, SINGAPORE | N41: =N40+P36+P37 -> 5863.92
A42: 48624
A43: Swift: UOVBSGSGXXX | N43: =N41-L35 -> 2560.6
A44: Acccount#: 4509022652 (USD)

Sheet PL-PO04786
A1: =+'INV-PO04774'!A2 -> CONTINENT 8 PTE LTD
A2: =+'INV-PO04774'!A3 -> 300 TAMPINES AVENUE 5, #. 09-02,
A3: =+'INV-PO04774'!A4 -> INCOME AT TAMPINES JUNCTION SINGAPORE 529653
A4: =+'INV-PO04774'!A5 -> AT TAMPINES JUNCTION SINGAPORE 529653
A5: PACKING LIST
J6: PO # | K6: =+'INV-PO04786'!I2 -> PO04786
A7: Consignee | F7: Notify Party | J7: Invoice NO. | K7: =+'INV-PO04786'!I3 -> 022C8P2605AW26.A
A8: Tentree c/o NRI Distribution Inc. | F8: =+'INV-PO04774'!D15 -> Tentree International Canada | J8: S/C NO. | K8: -
A9: 9988 Redwood Avenue | F9: =+'INV-PO04774'!D16 -> 230-1275 Venables St. | J9: Packinglist No. | K9: =K7 -> 022C8P2605AW26.A
A10: LH Building | F10: =+'INV-PO04774'!D17 -> Vancouver, BC V6A 2E4 | J10: DATE: | K10: =+'INV-PO04786'!I4 -> 46149
A11: Fontana, California | F11: =+'INV-PO04774'!D18 -> Canada | J11: PAGE: | K11: 1-1
A12: 1.323.345.6456 | F12: =+'INV-PO04774'!D19 -> +7789897887
A13: 92335, United States | F13: =+'INV-PO04774'!D20 -> logstics@tentree.com
A14: Contact: Yarumi Padilla
A15: 1.323.345.6456
A16: yarumi.padilla@nri-distribution.com
A17: Carrier Appointment Email
A19: CTN # | D19: PO # | E19: SKU | F19: UPC | G19: Style Description | H19: Color Description | I19: TOTAL CTN | J19: TOTAL PCS/CTN | K19: TOTAL PCS | L19: N/W (Kgs) | M19: G/W (Kgs) | N19: MEASURE (M3) | O19: MEASURE (CM)
A21: 1 | B21: - | C21: =+A21+I21-1 -> 1 | D21: =K6 -> PO04786 | E21: TCW6649-6303-2 | F21: 661814875897 | G21: =+'INV-PO04786'!D28 -> W Flint Pant | H21: =+'INV-PO04786'!E28 -> Ashwood | I21: 1 | J21: 2 | K21: =J21+J22+J23+J24+J25+J26+J27 -> 27 | L21: =540*J21/1000+560*J22/1000+580*J23/1000+600*J24/1000+620*J25/1000+640*J26/1000+660*J27/1000 -> 16.06 | M21: =1.65+L21 -> 17.71 | N21: 80 X 44 X 25 | O21: 2 | P21: 285 | Q21: 661814875897 | R21: 2
E22: TCW6649-6303-4 | F22: 661814875873 | J22: 5 | Q22: 661814875873 | R22: 4
E23: TCW6649-6303-6 | F23: 661814875859 | J23: 6 | Q23: 661814875859 | R23: 6
E24: TCW6649-6303-8 | F24: 661814875835 | J24: 5 | Q24: 661814875835 | R24: 8
E25: TCW6649-6303-10 | F25: 661814875972 | J25: 4 | Q25: 661814875972 | R25: 10
E26: TCW6649-6303-12 | F26: 661814875958 | J26: 4 | Q26: 661814875958 | R26: 12
E27: TCW6649-6303-14 | F27: 661814875934 | J27: 1 | Q27: 661814875934 | R27: 14
A28: =A21+I21 -> 2 | B28: - | C28: =+A28+I28-1 -> 2 | E28: TCW6649-0164-2 | F28: 661814876030 | H28: =+'INV-PO04786'!E29 -> Meteorite Black | I28: 1 | J28: 5 | K28: =J28+J29+J30+J31+J32+J33+J34 -> 29 | L28: =540*J28/1000+560*J29/1000+580*J30/1000+600*J31/1000+620*J32/1000+640*J33/1000+660*J34/1000 -> 17.12 | M28: =1.65+L28 -> 18.77 | N28: 80 X 44 X 25 | Q28: 661814876030 | R28: 2
E29: TCW6649-0164-4 | F29: 661814876016 | J29: 5 | Q29: 661814876016 | R29: 4
E30: TCW6649-0164-6 | F30: 661814875996 | J30: 5 | Q30: 661814875996 | R30: 6
E31: TCW6649-0164-8 | F31: 661814876054 | J31: 5 | Q31: 661814876054 | R31: 8
E32: TCW6649-0164-10 | F32: 661814876139 | J32: 4 | Q32: 661814876139 | R32: 10
E33: TCW6649-0164-12 | F33: 661814876115 | J33: 3 | Q33: 661814876115 | R33: 12
E34: TCW6649-0164-14 | F34: 661814876092 | J34: 2 | Q34: 661814876092 | R34: 14
A35: 1 | B35: - | C35: =+A35+I35-1 -> 1 | D35: =K6 -> PO04786 | E35: TCM6684-6303-30 | F35: 661814885612 | G35: =+'INV-PO04786'!D30 -> M Clark Pant | H35: =+'INV-PO04786'!E30 -> Ashwood | I35: 1 | J35: 3 | K35: =SUM(J35:J41) -> 18 | L35: =540*J35/1000+560*J36/1000+580*J37/1000+600*J38/1000+620*J39/1000+640*J40/1000+660*J41/1000 -> 10.82 | M35: =1.65+L35 -> 12.47 | N35: 80 X 44 X 25 | O35: 2 | P35: 285 | Q35: 661814885612 | R35: 30
E36: TCM6684-6303-31 | F36: 661814885599 | J36: 1 | Q36: 661814885599 | R36: 31
E37: TCM6684-6303-32 | F37: 661814885575 | J37: 4 | Q37: 661814885575 | R37: 32
E38: TCM6684-6303-33 | F38: 661814885551 | J38: 1 | Q38: 661814885551 | R38: 33
E39: TCM6684-6303-34 | F39: 661814885537 | J39: 4 | Q39: 661814885537 | R39: 34
E40: TCM6684-6303-36 | F40: 661814885513 | J40: 3 | Q40: 661814885513 | R40: 36
E41: TCM6684-6303-38 | F41: 661814885490 | J41: 2 | Q41: 661814885490 | R41: 38
A42: =A35+I35 -> 2 | B42: - | C42: =+A42+I42-1 -> 2 | E42: TCM6684-0164-30 | F42: 661814885773 | H42: =+'INV-PO04786'!E31 -> Meteorite Black | I42: 1 | J42: 8 | K42: =J42+J43+J44+J45 -> 26 | L42: =540*J42/1000+560*J43/1000+580*J44/1000+600*J45/1000 -> 14.84 | M42: =1.65+L42 -> 16.49 | N42: 80 X 44 X 25 | Q42: 661814885773 | R42: 30
E43: TCM6684-0164-31 | F43: 661814885759 | J43: 2 | Q43: 661814885759 | R43: 31
E44: TCM6684-0164-32 | F44: 661814885735 | J44: 10 | Q44: 661814885735 | R44: 32
E45: TCM6684-0164-33 | F45: 661814885711 | J45: 6 | Q45: 661814885711 | R45: 33
A46: =A42+I42 -> 3 | B46: - | C46: =+A46+I46-1 -> 3 | E46: TCM6684-0164-34 | F46: 661814885698 | I46: 1 | J46: 10 | K46: =J46+J47+J48+J49 -> 25 | L46: =620*J46/1000+640*J47/1000+660*J48/1000+680*J49/1000 -> 16 | M46: =1.65+L46 -> 17.65 | N46: 80 X 44 X 15 | Q46: 661814885698 | R46: 34
E47: TCM6684-0164-36 | F47: 661814885674 | J47: 7 | Q47: 661814885674 | R47: 36
E48: TCM6684-0164-38 | F48: 661814885650 | J48: 6 | Q48: 661814885650 | R48: 38
E49: TCM6684-0164-40 | F49: 661814885636 | J49: 2 | O49: 4 | P49: 288 | Q49: 661814885636 | R49: 40
A50: 1 | B50: - | C50: 1 | D50: =K6 -> PO04786 | E50: TCM6797-6289-L | F50: 661814886145 | G50: =+'INV-PO04786'!D32 -> M Simcoe Pant | H50: =+'INV-PO04786'!E32 -> Cedar Bark | I50: 1 | J50: 2 | K50: =J50+J51+J52 -> 5 | L50: =440*K50/1000 -> 2.2 | M50: =L50+0.72 -> 2.92 | N50: 80 X 44 X 15 | Q50: 661814886145 | R50: L
E51: TCM6797- 6289-M | F51: 661814886121 | J51: 2 | Q51: 661814886121 | R51: M
E52: TCM6797-6289-XL | F52: 661814885469 | J52: 1 | Q52: 661814885469 | R52: XL
A53: 1 | B53: - | C53: =+A53+I53-1 -> 1 | D53: =K6 -> PO04786 | E53: TCW5674-6391-S | F53: 661814889023 | G53: =+'INV-PO04786'!D33 -> W Yaletown Skirt | H53: =+'INV-PO04786'!E33 -> Meteorite Black/Meadowland Ditsy | I53: 1 | J53: 3 | K53: =J53+J54+J55 -> 9 | L53: =170*J53/1000+190*J54/1000+210*J55/1000 -> 1.69 | M53: =1.65+L53 -> 3.34 | N53: 80 X 44 X 15 | Q53: 661814889023 | R53: S
E54: TCW5674-6391-M | F54: 661814889047 | J54: 4 | Q54: 661814889047 | R54: M
E55: TCW5674-6391-L | F55: 661814889061 | J55: 2 | Q55: 661814889061 | R55: L
A57: GRAND TOTAL | I57: =SUM(I21:I56) -> 7 | J57: =SUM(J21:J56) -> 139 | K57: =SUM(K21:K56) -> 139 | L57: =SUM(L21:L56) -> 78.73 | M57: =SUM(M21:M56) -> 89.35 | N57: =P59 -> 0.5104 | P57: =80*44*25/1000000*4 -> 0.352
P58: =80*44*15/1000000*3 -> 0.1584
A59: SUMMARY | E59: XS | F59: S | G59: M | H59: L | I59: XL | J59: XXL | K59: SM | L59: LXL | M59: ONE | N59: TOTAL | P59: =SUM(P57:P58) -> 0.5104
A60: Style # | D60: Color # | E60: 2 | F60: 4 | G60: 6 | H60: 8 | I60: 10 | J60: 12 | K60: 14 | L60: 16
E61: 30 | F61: 31 | G61: 32 | H61: 33 | I61: 34 | J61: 36 | K61: 38 | L61: 40
A62: =+'INV-PO04786'!B28 -> TCW6649-6303 | D62: =+'INV-PO04786'!E28 -> Ashwood | E62: 2 | F62: 5 | G62: 6 | H62: 5 | I62: 4 | J62: 4 | K62: 1 | N62: =SUM(E62:M62) -> 27
A63: =+'INV-PO04786'!B29 -> TCW6649-0164 | D63: =+'INV-PO04786'!E29 -> Meteorite Black | E63: 5 | F63: 5 | G63: 5 | H63: 5 | I63: 4 | J63: 3 | K63: 2 | N63: =SUM(E63:M63) -> 29
A64: =+'INV-PO04786'!B30 -> TCM6684-6303 | D64: =+'INV-PO04786'!E30 -> Ashwood | E64: 3 | F64: 1 | G64: 4 | H64: 1 | I64: 4 | J64: 3 | K64: 2 | N64: =SUM(E64:M64) -> 18
A65: =+'INV-PO04786'!B31 -> TCM6684-0164 | D65: =+'INV-PO04786'!E31 -> Meteorite Black | E65: 8 | F65: 2 | G65: 10 | H65: 6 | I65: 10 | J65: 7 | K65: 6 | L65: 2 | N65: =SUM(E65:M65) -> 51
A66: =+'INV-PO04786'!B32 -> TCM6797-0164 | D66: =+'INV-PO04786'!E32 -> Cedar Bark | G66: 2 | H66: 2 | I66: 1 | N66: =SUM(E66:M66) -> 5
A67: =+'INV-PO04786'!B33 -> TCW5674-6391 | D67: =+'INV-PO04786'!E33 -> Meteorite Black/Meadowland Ditsy | F67: 3 | G67: 4 | H67: 2 | N67: =SUM(E67:M67) -> 9
A68: TOTAL SUMMARY | E68: =SUM(E62:E67) -> 18 | F68: =SUM(F62:F67) -> 16 | G68: =SUM(G62:G67) -> 31 | H68: =SUM(H62:H67) -> 21 | I68: =SUM(I62:I67) -> 23 | J68: =SUM(J62:J67) -> 17 | K68: =SUM(K62:K67) -> 11 | L68: =SUM(L62:L67) -> 2 | N68: =SUM(N62:N67) -> 139
A70: No of Units : | D70: =N68 -> 139 | E70: PCS
A71: No of cartons : | D71: =I57 -> 7 | E71: CTN
A72: Measurement : | D72: =N57 -> 0.5104 | E72: CBM
A73: Gross Weight : | D73: =M57 -> 89.35 | E73: KGS
A74: Net Weight : | D74: 78.73 | E74: KGS

Sheet CCI
B2: Revenue Canada | D2: Revenu Canada | E2: CANADA CUSTOMS INVOICE | O2: Page
B3: Customs and Excise | D3: Douanes et Accise | E3: FACTURE DES DOUANES CANADIANNES | O3: 1 | P3: of de1
A5: 1. Vendor (Name and Address)/Vendeur (Nom et adresse) | F5: 2. Date of Direct Shipment to Canada / Date d'expedition directe vers le Canada
A6: =+[16]INVOICE!A2 -> CONTINENT 8 PTE LTD | G6: =+'INV-PO04774'!I3 -> 022C8P2605AW26
A7: =+[16]INVOICE!A3 -> 300 TAMPINES AVENUE 5, #. 09-02,
A8: =+[16]INVOICE!A4 -> INCOME AT TAMPINES JUNCTION SINGAPORE 529653 | F8: 3. Other References (Include Purchaser's Order No.)
A9: =+[16]INVOICE!A5 -> AT TAMPINES JUNCTION SINGAPORE 529653 | F9: Autres references (inclure le no de commande de l'acheteur)
A11: 4. Consignee (Name and Address)/Destinataire (Nom et adresse) | F11: 5. Purchaser's Name and Address (if other than Consignee)
A12: =+[16]INVOICE!A15 -> NRI CA Warehouse (Ecomm) | F12: Nom et adresse de l'acheteur (S'il differe du destinataire)
A13: =+[16]INVOICE!A16 -> tentree c/o NRI Distribution Inc. - receiving
A14: =+[16]INVOICE!A17 -> 8205 Dallas Dr | F14: 6. Country of Transhipment / Pays de transbordement
A15: =+[16]INVOICE!A18 -> Kamloops, BC
A16: =+[16]INVOICE!A19 -> V2C 6X2, Canada | F16: 7. Country of Origin of Goods | K16: PACKINGSLIP NUMBER | N16: =G6 -> 022C8P2605AW26
A17: =+[16]INVOICE!A20 -> Contact: Alyssa Clisby | F17: Pays d'origine des marchandises | K17: PAYMENT TERM | M17: TT AFTER SIGHT
A18: =+[16]INVOICE!A21 -> 250 573 2619 | F18: INDONESIA
A19: =+[16]INVOICE!A22 -> Alyssa.Clisby@nri-distribution.com
A20: 8. Transportation : Give Mode and Place of Direct Shipment to Canada | F20: 9. Conditions of Sale and Terms of Payment
A21: Transport : Preciser mode et point d'expedition directe vers le Canada | F21: (i.e. Sale, Consignment Shipment, Leased Goods, etc.)
A22: SHIPPED BY: | B22: =+'INV-PO04774'!I5 -> SEA (INCRES 072N) | F22: Conditions de vente et modalites de paiement
A23: FROM : | B23: =+'INV-PO04774'!I9 -> JAKARTA, INDONESIA | F23: (p. ex. Vente, expedition en consignation, location de marchandises, etc.)
A24: TO : | B24: =+'INV-PO04774'!I10 -> LOS ANGLES, USA
A25: DATE : | B25: =+'INV-PO04774'!I7 -> 46153 | F25: 10. Currency of Settlement / Devises du paiement | K25: USD
A27: 11. No of | B27: 12. Spesification of Commodities (Kind of Packages, Marks and Numbers, General | K27: 13. Quantity | M27: Selling Price / Prix de vente
A28: Pkgs | B28: Description and Characteristics, I.e. Grade, Quality) | K28: (State Unit) | M28: 14. Unit Price | O28: 15. Total
A29: Nbre de | B29: Designation des articles (Nature des colis, marques et numeros, description generale | K29: Quantite | M29: Prix unitaire
A30: colis | B30: et caracteristiques, p. ex. Classe, qualite) | K30: (Preciser l'unite)
A31: =+#REF! -> #REF! | B31: PO#. | C31: =+[16]INVOICE!J2 -> PO04515
B32: STYLE-COLOR | C32: HS CODE | D32: UPC# | E32: DESCRIPTION | F32: CATAGORY | G32: GENDER | H32: COMPOSITION
B33: =+'INV-PO04774'!#REF! -> #REF! | C33: =+'INV-PO04774'!#REF! -> #REF! | D33: =+#REF! -> #REF! | E33: =+'INV-PO04774'!#REF! -> #REF! | F33: =+'INV-PO04774'!#REF! -> #REF! | G33: =+'INV-PO04774'!#REF! -> #REF! | H33: =+'INV-PO04774'!#REF! -> #REF! | K33: =+'INV-PO04774'!#REF! -> #REF! | L33: PCS | M33: USD | N33: =+'INV-PO04774'!#REF! -> #REF! | O33: USD | P33: =N33*K33 -> #REF!
B34: =+'INV-PO04774'!#REF! -> #REF! | C34: =+'INV-PO04774'!#REF! -> #REF! | D34: =+#REF! -> #REF! | E34: =+'INV-PO04774'!#REF! -> #REF! | F34: =+'INV-PO04774'!#REF! -> #REF! | G34: =+'INV-PO04774'!#REF! -> #REF! | H34: =+'INV-PO04774'!#REF! -> #REF! | K34: =+'INV-PO04774'!#REF! -> #REF! | L34: PCS | M34: USD | N34: =+'INV-PO04774'!#REF! -> #REF! | O34: USD | P34: =N34*K34 -> #REF!
B35: =+'INV-PO04774'!B28 -> TCW6649-6303 | C35: =+'INV-PO04774'!I28 -> 6104.62.62.20 | D35: =+#REF! -> #REF! | E35: =+'INV-PO04774'!D28 -> W Flint Pant | F35: =+'INV-PO04774'!F28 -> Pants | G35: =+'INV-PO04774'!G28 -> Womens | H35: =+'INV-PO04774'!H28 -> 53% Organic Cotton, 45% Recycled Polyester, 2% Spandex | K35: =+'INV-PO04774'!J28 -> 40 | L35: PCS | M35: USD | N35: =+'INV-PO04774'!K28 -> 23.35 | O35: USD | P35: =N35*K35 -> 934
B36: =+'INV-PO04774'!#REF! -> #REF! | C36: =+'INV-PO04774'!#REF! -> #REF! | D36: =+#REF! -> #REF! | E36: =+'INV-PO04774'!#REF! -> #REF! | F36: =+'INV-PO04774'!#REF! -> #REF! | G36: =+'INV-PO04774'!#REF! -> #REF! | H36: =+'INV-PO04774'!#REF! -> #REF! | K36: =+'INV-PO04774'!#REF! -> #REF! | L36: PCS | M36: USD | N36: =+'INV-PO04774'!#REF! -> #REF! | O36: USD | P36: =N36*K36 -> #REF!
B37: =+'INV-PO04774'!B30 -> TCM6684-6303 | C37: =+'INV-PO04774'!I30 -> 6103.42.62.20 | D37: =+#REF! -> #REF! | E37: =+'INV-PO04774'!D30 -> M Clark Pant | F37: =+'INV-PO04774'!F30 -> Pants | G37: =+'INV-PO04774'!G30 -> Mens | H37: =+'INV-PO04774'!H30 -> 53% Organic Cotton, 45% Recycled Polyester, 2% Spandex | K37: =+'INV-PO04774'!#REF! -> #REF! | L37: PCS | M37: USD | N37: =+'INV-PO04774'!#REF! -> #REF! | O37: USD | P37: =N37*K37 -> #REF!
B38: =+'INV-PO04774'!#REF! -> #REF! | C38: =+'INV-PO04774'!#REF! -> #REF! | D38: =+#REF! -> #REF! | E38: =+'INV-PO04774'!#REF! -> #REF! | F38: =+'INV-PO04774'!#REF! -> #REF! | G38: =+'INV-PO04774'!#REF! -> #REF! | H38: =+'INV-PO04774'!#REF! -> #REF! | K38: =+'INV-PO04774'!J35 -> 35 | L38: PCS | M38: USD | N38: =+'INV-PO04774'!K35 -> 27.48 | O38: USD | P38: =N38*K38 -> 961.8
B39: =+'INV-PO04774'!B32 -> TCW6648-6303 | C39: =+'INV-PO04774'!I32 -> 6204.63.62.10 | D39: =+#REF! -> #REF! | E39: =+'INV-PO04774'!D32 -> W Breton Pant | F39: =+'INV-PO04774'!F32 -> Pants | G39: =+'INV-PO04774'!G32 -> Womens | H39: =+'INV-PO04774'!H32 -> 90% Recycled Polyester, 10% Spandex | K39: =+'INV-PO04774'!#REF! -> #REF! | L39: PCS | M39: USD | N39: =+'INV-PO04774'!#REF! -> #REF! | O39: USD | P39: =N39*K39 -> #REF!
B40: =+'INV-PO04774'!#REF! -> #REF! | C40: =+'INV-PO04774'!#REF! -> #REF! | D40: =+#REF! -> #REF! | E40: =+'INV-PO04774'!#REF! -> #REF! | F40: =+'INV-PO04774'!#REF! -> #REF! | G40: =+'INV-PO04774'!#REF! -> #REF! | H40: =+'INV-PO04774'!#REF! -> #REF! | K40: =+'INV-PO04774'!#REF! -> #REF! | L40: PCS | M40: USD | N40: =+'INV-PO04774'!#REF! -> #REF! | O40: USD | P40: =N40*K40 -> #REF!
B41: =+'INV-PO04774'!#REF! -> #REF! | C41: =+'INV-PO04774'!#REF! -> #REF! | D41: =+#REF! -> #REF! | E41: =+'INV-PO04774'!#REF! -> #REF! | F41: =+'INV-PO04774'!#REF! -> #REF! | G41: =+'INV-PO04774'!#REF! -> #REF! | H41: =+'INV-PO04774'!#REF! -> #REF! | K41: =+'INV-PO04774'!J38 -> 46 | L41: PCS | M41: USD | N41: =+'INV-PO04774'!K38 -> 22.11 | O41: USD | P41: =N41*K41 -> 1017.06
B42: =+'INV-PO04774'!#REF! -> #REF! | C42: =+'INV-PO04774'!#REF! -> #REF! | D42: =+#REF! -> #REF! | E42: =+'INV-PO04774'!#REF! -> #REF! | F42: =+'INV-PO04774'!#REF! -> #REF! | G42: =+'INV-PO04774'!#REF! -> #REF! | H42: =+'INV-PO04774'!#REF! -> #REF! | K42: =+'INV-PO04774'!#REF! -> #REF! | L42: PCS | M42: USD | N42: =+'INV-PO04774'!#REF! -> #REF! | O42: USD | P42: =N42*K42 -> #REF!
B43: =+'INV-PO04774'!B35 -> TCM6685-6289 | C43: =+'INV-PO04774'!I35 -> 6203.43.62.10 | D43: =+#REF! -> #REF! | E43: =+'INV-PO04774'!D35 -> M Cameron Pant | F43: =+'INV-PO04774'!F35 -> Pants | G43: =+'INV-PO04774'!G35 -> Mens | H43: =+'INV-PO04774'!H35 -> 90% Recycled Polyester, 10% Spandex | K43: =+'INV-PO04774'!#REF! -> #REF! | L43: PCS | M43: USD | N43: =+'INV-PO04774'!#REF! -> #REF! | O43: USD | P43: =N43*K43 -> #REF!
B44: =+'INV-PO04774'!#REF! -> #REF! | C44: =+'INV-PO04774'!#REF! -> #REF! | D44: =+#REF! -> #REF! | E44: =+'INV-PO04774'!#REF! -> #REF! | F44: =+'INV-PO04774'!#REF! -> #REF! | G44: =+'INV-PO04774'!#REF! -> #REF! | H44: =+'INV-PO04774'!#REF! -> #REF! | K44: =+'INV-PO04774'!#REF! -> #REF! | L44: PCS | M44: USD | N44: =+'INV-PO04774'!#REF! -> #REF! | O44: USD | P44: =N44*K44 -> #REF!
B45: =+'INV-PO04774'!#REF! -> #REF! | C45: =+'INV-PO04774'!#REF! -> #REF! | D45: =+#REF! -> #REF! | E45: =+'INV-PO04774'!#REF! -> #REF! | F45: =+'INV-PO04774'!#REF! -> #REF! | G45: =+'INV-PO04774'!#REF! -> #REF! | H45: =+'INV-PO04774'!#REF! -> #REF! | K45: =+'INV-PO04774'!#REF! -> #REF! | L45: PCS | M45: USD | N45: =+'INV-PO04774'!#REF! -> #REF! | O45: USD | P45: =N45*K45 -> #REF!
B46: =+'INV-PO04774'!B36 -> TCW7113-6303 | C46: =+'INV-PO04774'!I36 -> 6204.63.62.10 | D46: =+#REF! -> #REF! | E46: =+'INV-PO04774'!D36 -> W Cowen Pant | F46: =+'INV-PO04774'!F36 -> Pants | G46: =+'INV-PO04774'!G36 -> Womens | H46: =+'INV-PO04774'!H36 -> 90% Recycled Polyester, 10% Spandex | K46: =+'INV-PO04774'!#REF! -> #REF! | L46: PCS | M46: USD | N46: =+'INV-PO04774'!#REF! -> #REF! | O46: USD | P46: =N46*K46 -> #REF!
B47: =+'INV-PO04774'!#REF! -> #REF! | C47: =+'INV-PO04774'!#REF! -> #REF! | D47: =+#REF! -> #REF! | E47: =+'INV-PO04774'!#REF! -> #REF! | F47: =+'INV-PO04774'!#REF! -> #REF! | G47: =+'INV-PO04774'!#REF! -> #REF! | H47: =+'INV-PO04774'!#REF! -> #REF! | K47: =+'INV-PO04774'!#REF! -> #REF! | L47: PCS | M47: USD | N47: =+'INV-PO04774'!#REF! -> #REF! | O47: USD | P47: =N47*K47 -> #REF!
B48: =+'INV-PO04774'!#REF! -> #REF! | C48: =+'INV-PO04774'!#REF! -> #REF! | D48: =+#REF! -> #REF! | E48: =+'INV-PO04774'!#REF! -> #REF! | F48: =+'INV-PO04774'!#REF! -> #REF! | G48: =+'INV-PO04774'!#REF! -> #REF! | H48: =+'INV-PO04774'!#REF! -> #REF! | K48: =+'INV-PO04774'!#REF! -> #REF! | L48: PCS | M48: USD | N48: =+'INV-PO04774'!#REF! -> #REF! | O48: USD | P48: =N48*K48 -> #REF!
B49: =+'INV-PO04774'!B38 -> TCM6797-0164 | C49: =+'INV-PO04774'!I38 -> 6203.43.62.10 | D49: =+#REF! -> #REF! | E49: =+'INV-PO04774'!D38 -> M Simcoe Pant | F49: =+'INV-PO04774'!F38 -> Pants | G49: =+'INV-PO04774'!G38 -> Mens | H49: =+'INV-PO04774'!H38 -> 90% Recycled Polyester, 10% Spandex | K49: =+'INV-PO04774'!J30 -> 50 | L49: PCS | M49: USD | N49: =+'INV-PO04774'!K30 -> 25.4 | O49: USD | P49: =N49*K49 -> 1270
B50: =+'INV-PO04774'!#REF! -> #REF! | C50: =+'INV-PO04774'!#REF! -> #REF! | D50: =+#REF! -> #REF! | E50: =+'INV-PO04774'!#REF! -> #REF! | F50: =+'INV-PO04774'!#REF! -> #REF! | G50: =+'INV-PO04774'!#REF! -> #REF! | H50: =+'INV-PO04774'!#REF! -> #REF! | K50: =+'INV-PO04774'!#REF! -> #REF! | L50: PCS | M50: USD | N50: =+'INV-PO04774'!#REF! -> #REF! | O50: USD | P50: =N50*K50 -> #REF!
B51: =+'INV-PO04774'!#REF! -> #REF! | C51: =+'INV-PO04774'!#REF! -> #REF! | D51: =+#REF! -> #REF! | E51: =+'INV-PO04774'!#REF! -> #REF! | F51: =+'INV-PO04774'!#REF! -> #REF! | G51: =+'INV-PO04774'!#REF! -> #REF! | H51: =+'INV-PO04774'!#REF! -> #REF! | K51: =+'INV-PO04774'!#REF! -> #REF! | L51: PCS | M51: USD | N51: =+'INV-PO04774'!#REF! -> #REF! | O51: USD | P51: =N51*K51 -> #REF!
B52: =+'INV-PO04774'!B39 -> TCW5674-6391 | C52: =+'INV-PO04774'!I39 -> 6204.63.62.10 | D52: =+#REF! -> #REF! | E52: =+'INV-PO04774'!D39 -> W Yaletown Skirt | F52: =+'INV-PO04774'!F39 -> Pants | G52: =+'INV-PO04774'!G39 -> Womens | H52: =+'INV-PO04774'!H39 -> 100% ECOVERO -Sustainable Viscose by Lenzing | K52: =+'INV-PO04774'!#REF! -> #REF! | L52: PCS | M52: USD | N52: =+'INV-PO04774'!#REF! -> #REF! | O52: USD | P52: =N52*K52 -> #REF!
B53: =+'INV-PO04774'!#REF! -> #REF! | C53: =+'INV-PO04774'!#REF! -> #REF! | D53: =+#REF! -> #REF! | E53: =+'INV-PO04774'!#REF! -> #REF! | F53: =+'INV-PO04774'!#REF! -> #REF! | G53: =+'INV-PO04774'!#REF! -> #REF! | H53: =+'INV-PO04774'!#REF! -> #REF! | K53: =+'INV-PO04774'!J32 -> 79 | L53: PCS | M53: USD | N53: =+'INV-PO04774'!K32 -> 21.85 | O53: USD | P53: =N53*K53 -> 1726.15
B54: =+'INV-PO04774'!#REF! -> #REF! | C54: =+'INV-PO04774'!#REF! -> #REF! | D54: =+#REF! -> #REF! | E54: =+'INV-PO04774'!#REF! -> #REF! | F54: =+'INV-PO04774'!#REF! -> #REF! | G54: =+'INV-PO04774'!#REF! -> #REF! | H54: =+'INV-PO04774'!#REF! -> #REF! | K54: =+'INV-PO04774'!#REF! -> #REF! | L54: PCS | M54: USD | N54: =+'INV-PO04774'!#REF! -> #REF! | O54: USD | P54: =N54*K54 -> #REF!
B55: =+'INV-PO04774'!#REF! -> #REF! | C55: =+'INV-PO04774'!#REF! -> #REF! | D55: =+#REF! -> #REF! | E55: =+'INV-PO04774'!#REF! -> #REF! | F55: =+'INV-PO04774'!#REF! -> #REF! | G55: =+'INV-PO04774'!#REF! -> #REF! | H55: =+'INV-PO04774'!#REF! -> #REF! | K55: =+'INV-PO04774'!J36 -> 41 | L55: PCS | M55: USD | N55: =+'INV-PO04774'!K36 -> 22.5 | O55: USD | P55: =N55*K55 -> 922.5
B56: =+'INV-PO04774'!#REF! -> #REF! | C56: =+'INV-PO04774'!#REF! -> #REF! | D56: =+#REF! -> #REF! | E56: =+'INV-PO04774'!#REF! -> #REF! | F56: =+'INV-PO04774'!#REF! -> #REF! | G56: =+'INV-PO04774'!#REF! -> #REF! | H56: =+'INV-PO04774'!#REF! -> #REF! | K56: =+'INV-PO04774'!#REF! -> #REF! | L56: PCS | M56: USD | N56: =+'INV-PO04774'!#REF! -> #REF! | O56: USD | P56: =N56*K56 -> #REF!
B57: =+'INV-PO04774'!#REF! -> #REF! | C57: =+'INV-PO04774'!#REF! -> #REF! | D57: =+#REF! -> #REF! | E57: =+'INV-PO04774'!#REF! -> #REF! | F57: =+'INV-PO04774'!#REF! -> #REF! | G57: =+'INV-PO04774'!#REF! -> #REF! | H57: =+'INV-PO04774'!#REF! -> #REF! | K57: =+'INV-PO04774'!#REF! -> #REF! | L57: PCS | M57: USD | N57: =+'INV-PO04774'!#REF! -> #REF! | O57: USD | P57: =N57*K57 -> #REF!
B58: =+'INV-PO04774'!#REF! -> #REF! | C58: =+'INV-PO04774'!#REF! -> #REF! | D58: =+#REF! -> #REF! | E58: =+'INV-PO04774'!#REF! -> #REF! | F58: =+'INV-PO04774'!#REF! -> #REF! | G58: =+'INV-PO04774'!#REF! -> #REF! | H58: =+'INV-PO04774'!#REF! -> #REF! | K58: =+'INV-PO04774'!J39 -> 149 | L58: PCS | M58: USD | N58: =+'INV-PO04774'!K39 -> 14.73 | O58: USD | P58: =N58*K58 -> 2194.77
B59: =+'INV-PO04774'!#REF! -> #REF! | C59: =+'INV-PO04774'!#REF! -> #REF! | D59: =+#REF! -> #REF! | E59: =+'INV-PO04774'!#REF! -> #REF! | F59: =+'INV-PO04774'!#REF! -> #REF! | G59: =+'INV-PO04774'!#REF! -> #REF! | H59: =+'INV-PO04774'!#REF! -> #REF! | K59: =+'INV-PO04774'!#REF! -> #REF! | L59: PCS | M59: USD | N59: =+'INV-PO04774'!#REF! -> #REF! | O59: USD | P59: =N59*K59 -> #REF!
B60: =+'INV-PO04774'!#REF! -> #REF! | C60: =+'INV-PO04774'!#REF! -> #REF! | D60: =+#REF! -> #REF! | E60: =+'INV-PO04774'!#REF! -> #REF! | F60: =+'INV-PO04774'!#REF! -> #REF! | G60: =+'INV-PO04774'!#REF! -> #REF! | H60: =+'INV-PO04774'!#REF! -> #REF! | K60: =+'INV-PO04774'!#REF! -> #REF! | L60: PCS | M60: USD | N60: =+'INV-PO04774'!#REF! -> #REF! | O60: USD | P60: =N60*K60 -> #REF!
B61: =+'INV-PO04774'!#REF! -> #REF! | C61: =+'INV-PO04774'!#REF! -> #REF! | D61: =+#REF! -> #REF! | E61: =+'INV-PO04774'!#REF! -> #REF! | F61: =+'INV-PO04774'!#REF! -> #REF! | G61: =+'INV-PO04774'!#REF! -> #REF! | H61: =+'INV-PO04774'!#REF! -> #REF! | K61: =+'INV-PO04774'!#REF! -> #REF! | L61: PCS | M61: USD | N61: =+'INV-PO04774'!#REF! -> #REF! | O61: USD | P61: =N61*K61 -> #REF!
B62: =+'INV-PO04774'!#REF! -> #REF! | C62: =+'INV-PO04774'!#REF! -> #REF! | D62: =+#REF! -> #REF! | E62: =+'INV-PO04774'!#REF! -> #REF! | F62: =+'INV-PO04774'!#REF! -> #REF! | G62: =+'INV-PO04774'!#REF! -> #REF! | H62: =+'INV-PO04774'!#REF! -> #REF! | K62: =+'INV-PO04774'!#REF! -> #REF! | L62: PCS | M62: USD | N62: =+'INV-PO04774'!#REF! -> #REF! | O62: USD | P62: =N62*K62 -> #REF!
B63: =+'INV-PO04774'!#REF! -> #REF! | C63: =+'INV-PO04774'!#REF! -> #REF! | D63: =+#REF! -> #REF! | E63: =+'INV-PO04774'!#REF! -> #REF! | F63: =+'INV-PO04774'!#REF! -> #REF! | G63: =+'INV-PO04774'!#REF! -> #REF! | H63: =+'INV-PO04774'!#REF! -> #REF! | K63: =+'INV-PO04774'!#REF! -> #REF! | L63: PCS | M63: USD | N63: =+'INV-PO04774'!#REF! -> #REF! | O63: USD | P63: =N63*K63 -> #REF!
B64: =+'INV-PO04774'!#REF! -> #REF! | C64: =+'INV-PO04774'!#REF! -> #REF! | D64: =+#REF! -> #REF! | E64: =+'INV-PO04774'!#REF! -> #REF! | F64: =+'INV-PO04774'!#REF! -> #REF! | G64: =+'INV-PO04774'!#REF! -> #REF! | H64: =+'INV-PO04774'!#REF! -> #REF! | K64: =+'INV-PO04774'!#REF! -> #REF! | L64: PCS | M64: USD | N64: =+'INV-PO04774'!#REF! -> #REF! | O64: USD | P64: =N64*K64 -> #REF!
B65: =+'INV-PO04774'!#REF! -> #REF! | C65: =+'INV-PO04774'!#REF! -> #REF! | D65: =+#REF! -> #REF! | E65: =+'INV-PO04774'!#REF! -> #REF! | F65: =+'INV-PO04774'!#REF! -> #REF! | G65: =+'INV-PO04774'!#REF! -> #REF! | H65: =+'INV-PO04774'!#REF! -> #REF! | K65: =+'INV-PO04774'!#REF! -> #REF! | L65: PCS | M65: USD | N65: =+'INV-PO04774'!#REF! -> #REF! | O65: USD | P65: =N65*K65 -> #REF!
B66: =+'INV-PO04774'!#REF! -> #REF! | C66: =+'INV-PO04774'!#REF! -> #REF! | D66: =+#REF! -> #REF! | E66: =+'INV-PO04774'!#REF! -> #REF! | F66: =+'INV-PO04774'!#REF! -> #REF! | G66: =+'INV-PO04774'!#REF! -> #REF! | H66: =+'INV-PO04774'!#REF! -> #REF! | K66: =+'INV-PO04774'!#REF! -> #REF! | L66: PCS | M66: USD | N66: =+'INV-PO04774'!#REF! -> #REF! | O66: USD | P66: =N66*K66 -> #REF!
B67: =+'INV-PO04774'!#REF! -> #REF! | C67: =+'INV-PO04774'!#REF! -> #REF! | D67: =+#REF! -> #REF! | E67: =+'INV-PO04774'!#REF! -> #REF! | F67: =+'INV-PO04774'!#REF! -> #REF! | G67: =+'INV-PO04774'!#REF! -> #REF! | H67: =+'INV-PO04774'!#REF! -> #REF! | K67: =+'INV-PO04774'!#REF! -> #REF! | L67: PCS | M67: USD | N67: =+'INV-PO04774'!#REF! -> #REF! | O67: USD | P67: =N67*K67 -> #REF!
B68: =+'INV-PO04774'!#REF! -> #REF! | C68: =+'INV-PO04774'!#REF! -> #REF! | D68: =+#REF! -> #REF! | E68: =+'INV-PO04774'!#REF! -> #REF! | F68: =+'INV-PO04774'!#REF! -> #REF! | G68: =+'INV-PO04774'!#REF! -> #REF! | H68: =+'INV-PO04774'!#REF! -> #REF! | K68: =+'INV-PO04774'!#REF! -> #REF! | L68: PCS | M68: USD | N68: =+'INV-PO04774'!#REF! -> #REF! | O68: USD | P68: =N68*K68 -> #REF!
B69: =+'INV-PO04774'!#REF! -> #REF! | C69: =+'INV-PO04774'!#REF! -> #REF! | D69: =+#REF! -> #REF! | E69: =+'INV-PO04774'!#REF! -> #REF! | F69: =+'INV-PO04774'!#REF! -> #REF! | G69: =+'INV-PO04774'!#REF! -> #REF! | H69: =+'INV-PO04774'!#REF! -> #REF! | K69: =+'INV-PO04774'!#REF! -> #REF! | L69: PCS | M69: USD | N69: =+'INV-PO04774'!#REF! -> #REF! | O69: USD | P69: =N69*K69 -> #REF!
B70: =+'INV-PO04774'!#REF! -> #REF! | C70: =+'INV-PO04774'!#REF! -> #REF! | D70: =+#REF! -> #REF! | E70: =+'INV-PO04774'!#REF! -> #REF! | F70: =+'INV-PO04774'!#REF! -> #REF! | G70: =+'INV-PO04774'!#REF! -> #REF! | H70: =+'INV-PO04774'!#REF! -> #REF! | K70: =+'INV-PO04774'!#REF! -> #REF! | L70: PCS | M70: USD | N70: =+'INV-PO04774'!#REF! -> #REF! | O70: USD | P70: =N70*K70 -> #REF!
... B88: =+'INV-PO04774'!#REF! -> #REF! | C88: =+'INV-PO04774'!#REF! -> #REF! | D88: =+#REF! -> #REF! | E88: =+'INV-PO04774'!#REF! -> #REF! | F88: =+'INV-PO04774'!#REF! -> #REF! | G88: =+'INV-PO04774'!#REF! -> #REF! | H88: =+'INV-PO04774'!#REF! -> #REF! | K88: =+'INV-PO04774'!#REF! -> #REF! | L88: PCS | M88: USD | N88: =+'INV-PO04774'!#REF! -> #REF! | O88: USD | P88: =N88*K88 -> #REF!
B89: CONTINENT 8 PTE LTD
B90: UNITED OVERSEAS BANK
B91: 80 RAFFLES PLACE, UOB PLAZA, SINGAPORE 048624
B92: Swift: UOVBSGSGXXX
B93: Acccount#: 450-902-2652 (USD)
K95: =SUM(K33:K93) -> #REF! | L95: PCS | O95: USD | P95: =SUM(P33:P94) -> #REF!
A96: 18. If any of fields 1 to 17 are included on an attached commercial invoice, check this box | K96: 16. Total Weight / Poids total | O96: 17. Invoice Total
A97: Si tout renseignement relativement aux zones 1 a 17 figure sur une ou des factures | K97: Net | M97: Gross / Brut | O97: Total de la facture
A98: commerciales ci-attachees, cocher cette case | K98: =+[16]DPL!B107 -> 398.862 | L98: KGS | M98: =+[16]DPL!B106 -> 462.162 | N98: KGS | O98: USD | P98: =P95 -> #REF!
A99: Commercial Invoice No. / No de la facture commerciale
A101: 19. Exporter's Name and Address (If other than Vendor) | F101: 20. Originator (Name and Address) / Expediteur d'origine (Nom et adresse)
A102: Nom et adresse de l'exportateur (s'il differe du vendeur)
A103: =+'INV-PO04774'!A8 -> PT. MASTERINDO JAYA ABADI
A104: =+'INV-PO04774'!A9 -> JL. SOEKARNO HATTA NO. 24
A105: =+'INV-PO04774'!A10 -> BANDUNG 40212, INDONESIA 50512
A106: =+'INV-PO04774'!A11 -> TAX ID#. 001.280.264.1-441.000
A108: 21. Departmental Ruling (If applicable) / Decision du Ministre (s'il y a lieu) | F108: 22. If fields 23 to 25 are not applicable, check this box
A109: FILE NO. 7465-2(LD), V5006-1" | F109: si les zones 23 a 25 sont sans object, cocher cette case | N109: X
A111: 23. If included in field 17 indicate amount : | K111: 25. Check (if applicable) :
A112: Si compris dans le total a la zone 17, preciser : | K112: Cocher (s'il y a lieu) :
B114: (I) Transportation charges, expenses and insurance | K114: (i) Royalty payments or subsequent proceeds are
B115: from the place of direct shipment to Canada | K115: paid or payable by the purchaser
B116: Les frais de transport, depenses at assurances | K116: Des redevances ou produits ont ete ou seront
B117: a partir du point d'expedition directe vers le | K117: verses par l'acheteur
B118: Canada
B121: (ii) Costs for construction, erection and assembly
B122: incurred after importation into Canada | K122: (ii) The purchaser has supplied goods or services
B123: Les couts de construction, d'erection et | K123: for use in the production of these goods
B124: d'assemblage apres importation au Canada | K124: L'acheteur a fourni des marchandises ou des
K125: services pour la production des marchandises
B127: (iii) Export packing
B128: Le cout de l'emballage d'exportation
A131: DEPARTMENT OF NATIONAL REVENUE - CUSTOMS AND EXCISE | K131: MINISTRE DU REVENU NATIONAL - DOUANES ET ACCISE

Sheet Instructions
A2: Tentree Commercial Invoice Instructions
A4: PO# | B4: Fill in PO number
A5: SKU# | B5: Use the full SKU number: style-color-size (TCM6418-6010-L)
A6: UPC# | B6: Use the corresponding UPC code related to the full SKU
A7: Knit/Woven | B7: Indicate if the item is Knitten or Woven, if neither insert "No"
A8: Style Description | B8: Written style description
A9: Color Description | B9: Written color description
A10: Category | B10: Choose from Dropdown
A11: Gender | B11: Choose from Dropdown (Men/Woman/Ungendered)
A12: Composition | B12: Written composition
A13: HTS Code | B13: Fill in HTS Code
A14: Quantity | B14: Quantity
A15: Unit Price | B15: Unit Price
A16: Total USD | B16: Quantity *Unit Price
